autocate/__init__.py
autocate/baselearners.py
autocate/core.py
autocate/evaluators.py
autocate/metalearners.py
autocate/preprocessors.py
autocate/utils.py
autocate-0.1.0.dist-info/licenses/LICENSE
autocate-0.1.0.dist-info/METADATA
autocate-0.1.0.dist-info/WHEEL
autocate-0.1.0.dist-info/top_level.txt
autocate-0.1.0.dist-info/RECORD
